basil/__init__.py
basil/dut.py
basil/HL/Arduino.py
basil/HL/FEI4AdapterCard.py
basil/HL/FEI4QuadModuleAdapterCard.py
basil/HL/FadcConf.py
basil/HL/GPAC.py
basil/HL/HardwareLayer.py
basil/HL/JtagGpio.py
basil/HL/JtagMaster.py
basil/HL/MIO_PLL.py
basil/HL/NTCRegister.py
basil/HL/RegisterHardwareLayer.py
basil/HL/SensirionBridgeDevice.py
basil/HL/SignatoneProber.py
basil/HL/SussProber.py
basil/HL/__init__.py
basil/HL/agilent33250a.py
basil/HL/agilent_33250a.yaml
basil/HL/agilent_e3644a.yaml
basil/HL/binder_mk53.py
basil/HL/bram_fifo.py
basil/HL/bronkhorst_elflow.py
basil/HL/cmd_seq.py
basil/HL/debyeflex3003.py
basil/HL/fadc_rx.py
basil/HL/fast_spi_rx.py
basil/HL/fei4_rx.py
basil/HL/gpio.py
basil/HL/hp_81104a.yaml
basil/HL/i2c.py
basil/HL/iseg_shq.py
basil/HL/julaboF32HD.py
basil/HL/keithley_2000.yaml
basil/HL/keithley_2001.yaml
basil/HL/keithley_2400.yaml
basil/HL/keithley_2410.yaml
basil/HL/keithley_2450.yaml
basil/HL/keithley_2460.yaml
basil/HL/keithley_2602a.yaml
basil/HL/keithley_2634b.yaml
basil/HL/keithley_6517a.yaml
basil/HL/m26_rx.py
basil/HL/mercury.py
basil/HL/pulse_gen.py
basil/HL/scpi.py
basil/HL/scpi_sim_device.yaml
basil/HL/sensirion_ekh4.py
basil/HL/sensirion_sht85.py
basil/HL/seq_gen.py
basil/HL/seq_rec.py
basil/HL/si570.py
basil/HL/sitcp_fifo.py
basil/HL/spi.py
basil/HL/sram_fifo.py
basil/HL/tdc_s3.py
basil/HL/tektronix_mso4034.yaml
basil/HL/tektronix_mso4104b.yaml
basil/HL/timestamp.py
basil/HL/tlu.py
basil/HL/tti_ql355tp.py
basil/HL/tti_ql355tp.yaml
basil/HL/weiss_labevent.py
basil/HL/weiss_sb22.py
basil/RL/FunctionalRegister.py
basil/RL/RegisterLayer.py
basil/RL/StdRegister.py
basil/RL/TrackRegister.py
basil/RL/__init__.py
basil/TL/Dummy.py
basil/TL/SensirionSensorBridge.py
basil/TL/Serial.py
basil/TL/SiSim.py
basil/TL/SiTcp.py
basil/TL/SiTransferLayer.py
basil/TL/SiUart.py
basil/TL/SiUsb.py
basil/TL/SiUsb3.py
basil/TL/Socket.py
basil/TL/TransferLayer.py
basil/TL/Visa.py
basil/TL/__init__.py
basil/firmware/Arduino/Arduino.ino
basil_daq-3.2.0.dist-info/LICENSE.txt
basil_daq-3.2.0.dist-info/METADATA
basil_daq-3.2.0.dist-info/WHEEL
basil_daq-3.2.0.dist-info/top_level.txt
basil_daq-3.2.0.dist-info/RECORD
