Metadata-Version: 2.1
Name: basil-daq
Version: 3.2.0
Summary: Basil - a data acquisition and system testing framework
Home-page: https://github.com/SiLab-Bonn/basil
Author: Tomasz Hemperek, Jens Janssen, David-Leon Pohl
Author-email: hemperek@uni-bonn.de, janssen@physik.uni-bonn.de, pohl@physik.uni-bonn.de
Maintainer: Tomasz Hemperek, Jens Janssen, David-Leon Pohl
License: BSD 3-Clause ("BSD New" or "BSD Simplified") License
Platform: any
Requires-Python: >=3.7
License-File: LICENSE.txt
Requires-Dist: numpy
Requires-Dist: pyyaml
Requires-Dist: bitarray (>=2.0.0)
Requires-Dist: six
